torchvinecopulib/__init__.py
torchvinecopulib/bicop/__init__.py
torchvinecopulib/bicop/_abc.py
torchvinecopulib/bicop/_archimedean.py
torchvinecopulib/bicop/_clayton.py
torchvinecopulib/bicop/_data_bcp.py
torchvinecopulib/bicop/_elliptical.py
torchvinecopulib/bicop/_factory_bcp.py
torchvinecopulib/bicop/_frank.py
torchvinecopulib/bicop/_gaussian.py
torchvinecopulib/bicop/_gumbel.py
torchvinecopulib/bicop/_independent.py
torchvinecopulib/bicop/_joe.py
torchvinecopulib/bicop/_studentt.py
torchvinecopulib/util/__init__.py
torchvinecopulib/vinecop/__init__.py
torchvinecopulib/vinecop/_data_vcp.py
torchvinecopulib/vinecop/_factory_vcp.py
torchvinecopulib-2024.12.5.dist-info/LICENSE
torchvinecopulib-2024.12.5.dist-info/METADATA
torchvinecopulib-2024.12.5.dist-info/WHEEL
torchvinecopulib-2024.12.5.dist-info/RECORD
