Metadata-Version: 2.1
Name: torchvinecopulib
Version: 2024.12.5
Summary: yet another vine copula library for PyTorch.
Home-page: https://github.com/TY-Cheng/torchvinecopulib
License: GNU GPLv3
Keywords: vine copula,copula,torch
Author: Tuoyuan Cheng
Author-email: tuoyuan.cheng@nus.edu.sg
Maintainer: Xiaosheng You
Maintainer-email: e1204754@u.nus.edu
Requires-Python: >=3.10,<4.0
Classifier: Environment :: GPU :: NVIDIA CUDA :: 12 :: 12.1
Classifier: License :: OSI Approved :: GNU General Public License v3 (GPLv3)
Classifier: License :: Other/Proprietary License
Classifier: Operating System :: MacOS
Classifier: Operating System :: Microsoft :: Windows :: Windows 10
Classifier: Operating System :: POSIX :: Linux
Classifier: Programming Language :: Python :: 3
Classifier: Programming Language :: Python :: 3.10
Classifier: Programming Language :: Python :: 3.11
Classifier: Programming Language :: Python :: 3.12
Classifier: Programming Language :: Python :: 3.13
Classifier: Topic :: Scientific/Engineering
Provides-Extra: dev-cpu
Provides-Extra: dev-cuda
Requires-Dist: numpy
Requires-Dist: scipy
Requires-Dist: torch (>=2,<3) ; extra == "dev-cpu" or extra == "dev-cuda"
Project-URL: Bug Tracker, https://github.com/TY-Cheng/torchvinecopulib/issues/new
Project-URL: Documentation, https://ty-cheng.github.io/torchvinecopulib/
Project-URL: Repository, https://github.com/TY-Cheng/torchvinecopulib
